{
  "bible_seen": 74,
  "bible_target": 6,
  "bible_total": 80,
  "dev_examples": 100850,
  "ner_seen": 78,
  "ner_target": 6,
  "ner_total": 84,
  "plan_unverified": 0,
  "pos_seen": 58,
  "pos_target": 0,
  "pos_total": 58,
  "pppl_seen": 92,
  "pppl_target": 10,
  "pppl_total": 102,
  "roundtrip_seen": 74,
  "roundtrip_target": 6,
  "roundtrip_total": 80,
  "seen92": 92,
  "source_examples": 1169433406,
  "target10": 10,
  "tatoeba_seen": 63,
  "tatoeba_target": 3,
  "tatoeba_total": 66,
  "taxi1500_seen": 1,
  "taxi1500_target": 0,
  "taxi1500_total": 1,
  "test_examples": 100851,
  "total_languages": 102,
  "train_examples": 1169231705,
  "xlmr_seen_no": 10,
  "xlmr_seen_yes": 92
}
